{
  "ignorePatterns": [
    { "pattern": "^#.*" },
    { "pattern": ".*dev/proto/core.*" },
    { "pattern": "script.svg" },
    { "pattern": "^https://vscode.dev" },
    { "pattern": "^https://graphdb.ontotext.com" },
    { "pattern": "^https://virtuoso.openlinksw.com" },
    { "pattern": "^https://tiddlywiki.com" },
    { "pattern": "^https://marketplace.visualstudio.com" },
    { "pattern": "^https://www.hl7.org/fhir/" },
    { "pattern": "^https://metaphacts.com" }
  ],
  "aliveStatusCodes": [503, 502, 405, 200, 0]
}
